dictencli/__init__.py
dictencli/dictencli.py
dictencli-0.1.2.dist-info/entry_points.txt
dictencli-0.1.2.dist-info/WHEEL
dictencli-0.1.2.dist-info/METADATA
dictencli-0.1.2.dist-info/RECORD
