Metadata-Version: 2.1
Name: dictencli
Version: 0.1.2
Summary: A simple commandline dictionary app.
Author: Nikhil
Author-email: nikhilomkar99@gmail.com
Requires-Python: >=3.8,<4.0
Classifier: Programming Language :: Python :: 3
Classifier: Programming Language :: Python :: 3.10
Classifier: Programming Language :: Python :: 3.8
Classifier: Programming Language :: Python :: 3.9
Requires-Dist: Pygments (>=2.11.2,<3.0.0)
Requires-Dist: certifi (>=2021.10.8,<2022.0.0)
Requires-Dist: charset-normalizer (>=2.0.12,<3.0.0)
Requires-Dist: click (>=8.0.3,<9.0.0)
Requires-Dist: colorama (>=0.4.4,<0.5.0)
Requires-Dist: commonmark (>=0.9.1,<0.10.0)
Requires-Dist: idna (>=3.3,<4.0)
Requires-Dist: playsound (>=1.2.2,<2.0.0)
Requires-Dist: requests (>=2.27.1,<3.0.0)
Requires-Dist: rich (>=11.2.0,<12.0.0)
Requires-Dist: typer (>=0.4.0,<0.5.0)
Requires-Dist: urllib3 (>=1.26.8,<2.0.0)
